<?xml version="1.0" encoding="utf-8"?>
<key id="3e82c536-ee6c-45f4-b40d-0bfdaf1b3ac3" version="1">
  <creationDate>2025-09-24T22:45:22.2089016Z</creationDate>
  <activationDate>2025-09-24T22:45:22.1163498Z</activationDate>
  <expirationDate>2025-12-23T22:45:22.1163498Z</expirationDate>
  <descriptor deserializerType="Microsoft.AspNetCore.DataProtection.AuthenticatedEncryption.ConfigurationModel.AuthenticatedEncryptorDescriptorDeserializer, Microsoft.AspNetCore.DataProtection, Version=8.0.0.0, Culture=neutral, PublicKeyToken=adb9793829ddae60">
    <descriptor>
      <encryption algorithm="AES_256_CBC" />
      <validation algorithm="HMACSHA256" />
      <masterKey p4:requiresEncryption="true" xmlns:p4="http://schemas.asp.net/2015/03/dataProtection">
        <!-- Warning: the key below is in an unencrypted form. -->
        <value>smhBSPPfDggYnvHOI/vbDQxerQjsG8D86Bw1U7Iv1qgZdq2yY/q6BGVQSvlQr47vq5SWpXDkfMf5IL8futkiUg==</value>
      </masterKey>
    </descriptor>
  </descriptor>
</key>